{
  "recipe": {
    "title": {
      "type": "string",
      "validators": ["required"]
    },
    "description": {
      "type": "text",
      "validators": ["required"]
    },
    "imageURL": {
      "type": "string",
      "validators": []
    },
    "portions": {
      "type": "integer",
      "validators": ["required"]
    },
    "time": {
      "type": "integer",
      "validators": ["required"]
    },
    "ingredients": {
      "type": "text",
      "validators": ["required"]
    }
  }
}
